terraformmetrics/__init__.py
terraformmetrics/command_line.py
terraformmetrics/import_metrics.py
terraformmetrics/lines_metric.py
terraformmetrics/metrics_extractor.py
terraformmetrics/terraform_metric.py
terraformmetrics/general/__init__.py
terraformmetrics/general/lines_blank.py
terraformmetrics/general/lines_code.py
terraformmetrics/general/lines_comment.py
terraformmetrics/general/num_conditions.py
terraformmetrics/general/num_decisions.py
terraformmetrics/general/num_math_operations.py
terraformmetrics/general/num_tokens.py
terraformmetrics/general/text_entropy.py
terraformmetrics/terraformspec/__init__.py
terraformmetrics/terraformspec/avg_resource_size.py
terraformmetrics/terraformspec/num_data_sources.py
terraformmetrics/terraformspec/num_depends_on.py
terraformmetrics/terraformspec/num_dynamic_blocks.py
terraformmetrics/terraformspec/num_error_handling.py
terraformmetrics/terraformspec/num_file_provisioner.py
terraformmetrics/terraformspec/num_http_datasource.py
terraformmetrics/terraformspec/num_local.py
terraformmetrics/terraformspec/num_modules.py
terraformmetrics/terraformspec/num_output.py
terraformmetrics/terraformspec/num_path.py
terraformmetrics/terraformspec/num_permissions.py
terraformmetrics/terraformspec/num_provider.py
terraformmetrics/terraformspec/num_regex.py
terraformmetrics/terraformspec/num_remote_exec.py
terraformmetrics/terraformspec/num_resources.py
terraformmetrics/terraformspec/num_var.py
terraformmetrics-1.0.6.dist-info/METADATA
terraformmetrics-1.0.6.dist-info/WHEEL
terraformmetrics-1.0.6.dist-info/entry_points.txt
terraformmetrics-1.0.6.dist-info/top_level.txt
terraformmetrics-1.0.6.dist-info/RECORD
